witticism/__init__.py
witticism/_version.py
witticism/main.py
witticism/assets/witticism.ico
witticism/assets/witticism.png
witticism/assets/witticism_128x128.png
witticism/assets/witticism_16x16.png
witticism/assets/witticism_24x24.png
witticism/assets/witticism_256x256.png
witticism/assets/witticism_32x32.png
witticism/assets/witticism_48x48.png
witticism/assets/witticism_512x512.png
witticism/assets/witticism_64x64.png
witticism/core/audio_capture.py
witticism/core/continuous_transcriber.py
witticism/core/dependency_validator.py
witticism/core/hotkey_manager.py
witticism/core/mock_whisperx.py
witticism/core/transcription_pipeline.py
witticism/core/whisperx_engine.py
witticism/platform/__init__.py
witticism/platform/sleep_monitor.py
witticism/ui/about_dialog.py
witticism/ui/cuda_health_dialog.py
witticism/ui/hotkey_input_widget.py
witticism/ui/icon_utils.py
witticism/ui/settings_dialog.py
witticism/ui/system_tray.py
witticism/utils/config_manager.py
witticism/utils/logging_config.py
witticism/utils/output_manager.py
witticism-0.8.0.dist-info/licenses/LICENSE
witticism-0.8.0.dist-info/METADATA
witticism-0.8.0.dist-info/WHEEL
witticism-0.8.0.dist-info/entry_points.txt
witticism-0.8.0.dist-info/top_level.txt
witticism-0.8.0.dist-info/RECORD
