Metadata-Version: 2.4
Name: witticism
Version: 0.8.0
Summary: WhisperX-powered global transcription and push-to-talk application
Author-email: Aaron Stannard <aaron@petabridge.com>
License-Expression: Apache-2.0
Keywords: transcription,whisperx,speech-recognition,push-to-talk
Classifier: Development Status :: 4 - Beta
Classifier: Intended Audience :: End Users/Desktop
Classifier: Programming Language :: Python :: 3
Classifier: Programming Language :: Python :: 3.9
Classifier: Programming Language :: Python :: 3.10
Classifier: Programming Language :: Python :: 3.11
Classifier: Programming Language :: Python :: 3.12
Classifier: Topic :: Multimedia :: Sound/Audio :: Speech
Requires-Python: <3.13,>=3.9
License-File: LICENSE
Requires-Dist: whisperx>=3.1.0
Requires-Dist: torch<2.8.0,>=2.0.0
Requires-Dist: torchaudio<2.9.0,>=2.0.0
Requires-Dist: PyQt5>=5.15.0
Requires-Dist: pyaudio>=0.2.11
Requires-Dist: pynput>=1.7.0
Requires-Dist: webrtcvad-wheels>=2.0.14
Requires-Dist: numpy>=1.20.0
Requires-Dist: pyperclip>=1.8.0
Requires-Dist: platformdirs>=3.0.0
Requires-Dist: pydbus>=0.6.0; sys_platform == "linux"
Dynamic: license-file
